apna_python_experiment_sdk/__init__.py
apna_python_experiment_sdk/apna_experiment_tracker.py
apna_python_experiment_sdk/constants.py
apna_python_experiment_sdk/base/__init__.py
apna_python_experiment_sdk/base/configuration.py
apna_python_experiment_sdk/base/sink.py
apna_python_experiment_sdk/base/sink_serializer.py
apna_python_experiment_sdk/base/tracker.py
apna_python_experiment_sdk/custom/__init__.py
apna_python_experiment_sdk/custom/mixpanel/__init__.py
apna_python_experiment_sdk/custom/mixpanel/async_mixpanel_buffered_consumer.py
apna_python_experiment_sdk/defaults/__init__.py
apna_python_experiment_sdk/defaults/default_unleash_client.py
apna_python_experiment_sdk/defaults/sinks/__init__.py
apna_python_experiment_sdk/defaults/sinks/async_mixpanel_sink.py
apna_python_experiment_sdk/defaults/sinks/mixpanel_sink.py
apna_python_experiment_sdk/defaults/sinks/rudderstack.py
apna_python_experiment_sdk/factories/__init__.py
apna_python_experiment_sdk/factories/experiment_client.py
apna_experiment_sdk-0.4.10.dist-info/METADATA
apna_experiment_sdk-0.4.10.dist-info/WHEEL
apna_experiment_sdk-0.4.10.dist-info/top_level.txt
apna_experiment_sdk-0.4.10.dist-info/RECORD
