Metadata-Version: 2.1
Name: apna-experiment-sdk
Version: 0.4.10
Summary: This is the SDK for fetching variants in experiments and tracking it to sinks like Bigquery and Mixpanel.
Home-page: 
Author: Deval Sethi
Author-email: devals@apna.co
Keywords: pip,experiment
Requires-Dist: rudder-sdk-python >=1.0.0b1
Requires-Dist: UnleashClient >=4.4.1
Requires-Dist: python-dotenv >=0.19.1
Requires-Dist: mixpanel >=4.9.0
